LICENSE.txt
MANIFEST.in
README.md
markdown_map.py
secretary.py
setup.py
simple_template.odt
secretary.egg-info/PKG-INFO
secretary.egg-info/SOURCES.txt
secretary.egg-info/dependency_links.txt
secretary.egg-info/requires.txt
secretary.egg-info/top_level.txt