Metadata-Version: 1.1
Name: secretary
Version: 0.0.2
Summary: Take the power of Jinja2 templates to OpenOffice and LibreOffice and create reports and letters in your web applications
Home-page: https://github.com/christopher-ramirez/secretary
Author: Christopher Ramírez
Author-email: chris.ramirezg@gmail.com
License: BSD
Platform: any
Classifier: Environment :: Web Environment
Classifier: Intended Audience :: End Users/Desktop
Classifier: Operating System :: OS Independent
Classifier: Programming Language :: Python
Classifier: Development Status :: 3 - Alpha
Classifier: Topic :: Software Development :: Libraries :: Python Modules
Classifier: Topic :: Office/Business
Classifier: Topic :: Utilities
